<?xml version="1.0" encoding="UTF-8"?>
<datamodel>
    <database name="jpetstore">
        <connection
                type="jdbc"
                driver="org.postgresql.Driver"
                url="jdbc:postgresql://127.0.0.1:5432/jpetstore"
                username="manydesigns"
                password="manydesigns"/>
        <schemas>
            <schema name="public">
                <tables>
                    <table name="category">
                        <columns>
                            <column name="catid"
                                    columnType="VARCHAR"
                                    javaType="java.lang.String"
                                    length="10"
                                    nullable="false"/>
                            <column name="name"
                                    columnType="VARCHAR"
                                    javaType="java.lang.String"
                                    length="80"
                                    nullable="true"/>
                            <column name="descn"
                                    columnType="VARCHAR"
                                    javaType="java.lang.String"
                                    length="255"
                                    nullable="true"/>
                        </columns>
                        <primaryKey name="pk_category">
                            <column name="catid"/>
                        </primaryKey>
                    </table>
                    <table name="product">
                        <columns>
                            <column name="productid"
                                    columnType="VARCHAR"
                                    javaType="java.lang.String"
                                    length="10"
                                    nullable="false"/>
                            <column name="category"
                                    columnType="VARCHAR"
                                    javaType="java.lang.String"
                                    length="10"
                                    nullable="false"/>
                            <column name="name"
                                    columnType="VARCHAR"
                                    javaType="java.lang.String"
                                    length="80"
                                    nullable="true"/>
                            <column name="descn"
                                    columnType="VARCHAR"
                                    javaType="java.lang.String"
                                    length="255"
                                    nullable="true"/>
                        </columns>
                        <primaryKey name="pk_category">
                            <column name="productid"/>
                        </primaryKey>
                        <relationships>
                            <relationship name="fk_product_1"
                                          toSchema="public"
                                          toTable="category"
                                          onUpdate="NO ACTION"
                                          onDelete="NO ACTION">
                                <reference fromColumn="category"
                                           toColumn="catid"/>
                            </relationship>
                        </relationships>
                    </table>
                </tables>
            </schema>
        </schemas>
    </database>
</datamodel>